Metadata-Version: 2.1
Name: pack2048
Version: 0.4.0
Summary: Un module pour résoudre le 2048
Home-page: UNKNOWN
Author: Jérémy Duron
Author-email: jlmncddgg@gmail.com
License: UNKNOWN
Platform: UNKNOWN
Classifier: Development Status :: 4 - Beta
Classifier: License :: OSI Approved :: GNU Affero General Public License v3 or later (AGPLv3+)
Classifier: Programming Language :: Python :: 3.7
